redback_surrogates/__init__.py
redback_surrogates/afterglowmodels.py
redback_surrogates/data_management.py
redback_surrogates/kilonovamodels.py
redback_surrogates/model_library.py
redback_surrogates/supernovamodels.py
redback_surrogates/utils.py
redback_surrogates/surrogate_data/bulla-bhns-latent-2-hidden-500-CV-4.pt
redback_surrogates/surrogate_data/bulla-bns-latent-20-hidden-1000-CV-4.pt
redback_surrogates/surrogate_data/kasen-bns-latent-10-hidden-500-CV-4.pt
redback_surrogates/surrogate_data/metadata_bulla_bhns.json
redback_surrogates/surrogate_data/metadata_bulla_bns.json
redback_surrogates/surrogate_data/metadata_kasen_bns.json
redback_surrogates/surrogate_data/tophat_redback_300x3.pkl
redback_surrogates/surrogate_data/tophat_redback_scalex.pkl
redback_surrogates/surrogate_data/tophat_redback_scaley.pkl
redback_surrogates-0.2.6.dist-info/licenses/LICENCE.md
redback_surrogates-0.2.6.dist-info/METADATA
redback_surrogates-0.2.6.dist-info/WHEEL
redback_surrogates-0.2.6.dist-info/top_level.txt
redback_surrogates-0.2.6.dist-info/RECORD
