Metadata-Version: 2.4
Name: redback_surrogates
Version: 0.2.6
Summary: A surrogates package to work with redback, the bayesian inference package for electromagnetic transients
Home-page: https://github.com/nikhil-sarin/redback_surrogates
Author: Nikhil Sarin
Author-email: nsarin.astro@gmail.com
License: GNU General Public License v3 (GPLv3)
Classifier: Programming Language :: Python :: 3
Classifier: License :: OSI Approved :: GNU General Public License v3 (GPLv3)
Classifier: Operating System :: OS Independent
Requires-Python: >=3.10
License-File: LICENCE.md
Requires-Dist: setuptools
Requires-Dist: numpy
Requires-Dist: tqdm
Requires-Dist: pyphot==1.6.0
Requires-Dist: pandas
Requires-Dist: scipy
Requires-Dist: scikit_learn
Requires-Dist: matplotlib
Requires-Dist: lxml
Requires-Dist: sphinx-rtd-theme
Requires-Dist: sphinx-tabs
Requires-Dist: kilonovanet
Requires-Dist: tensorflow
Requires-Dist: keras
Provides-Extra: all
Requires-Dist: bilby; extra == "all"
Dynamic: author
Dynamic: author-email
Dynamic: classifier
Dynamic: description
Dynamic: description-content-type
Dynamic: home-page
Dynamic: license
Dynamic: license-file
Dynamic: provides-extra
Dynamic: requires-dist
Dynamic: requires-python
Dynamic: summary
